[
  {
    "slug": "duxontv",
    "platform": "kick",
    "live": true,
    "viewers": 0,
    "thumb": "https://stream.kick.com/thumbnails/livestream/94928567/thumb0/video_thumbnail/thumb0.jpg",
    "updatedAt": "2026-02-03T06:32:27.775Z"
  },
  {
    "slug": "ferchucabj",
    "platform": "kick",
    "live": true,
    "viewers": 0,
    "thumb": "https://stream.kick.com/thumbnails/livestream/94976888/thumb0/video_thumbnail/thumb0.jpg",
    "updatedAt": "2026-02-03T06:32:25.521Z"
  },
  {
    "slug": "iemmanuel",
    "platform": "kick",
    "live": true,
    "viewers": 0,
    "thumb": "https://stream.kick.com/thumbnails/livestream/94935443/thumb0/video_thumbnail/thumb0.jpg",
    "updatedAt": "2026-02-03T06:32:26.231Z"
  },
  {
    "slug": "shotbywolf",
    "platform": "kick",
    "live": true,
    "viewers": 0,
    "thumb": "https://stream.kick.com/thumbnails/livestream/94944725/thumb0/video_thumbnail/thumb0.jpg",
    "updatedAt": "2026-02-03T06:32:27.729Z"
  },
  {
    "slug": "9kemo",
    "platform": "kick",
    "live": false,
    "viewers": 0,
    "thumb": null,
    "updatedAt": "2026-02-03T06:32:25.859Z"
  },
  {
    "slug": "agusss04",
    "platform": "kick",
    "live": false,
    "viewers": 0,
    "thumb": null,
    "updatedAt": "2026-02-03T06:32:25.923Z"
  },
  {
    "slug": "chali",
    "platform": "kick",
    "live": false,
    "viewers": 0,
    "thumb": null,
    "updatedAt": "2026-02-03T06:32:24.820Z"
  },
  {
    "slug": "chinoxzzz",
    "platform": "kick",
    "live": false,
    "viewers": 0,
    "thumb": null,
    "updatedAt": "2026-02-03T06:32:26.983Z"
  },
  {
    "slug": "daytetona",
    "platform": "kick",
    "live": false,
    "viewers": 0,
    "thumb": null,
    "updatedAt": "2026-02-03T06:32:26.747Z"
  },
  {
    "slug": "eldaka",
    "platform": "kick",
    "live": false,
    "viewers": 0,
    "thumb": null,
    "updatedAt": "2026-02-03T06:32:25.284Z"
  },
  {
    "slug": "feleen",
    "platform": "kick",
    "live": false,
    "viewers": 0,
    "thumb": null,
    "updatedAt": "2026-02-03T06:32:26.409Z"
  },
  {
    "slug": "flakitomj",
    "platform": "kick",
    "live": false,
    "viewers": 0,
    "thumb": null,
    "updatedAt": "2026-02-03T06:32:27.591Z"
  },
  {
    "slug": "g4spl",
    "platform": "kick",
    "live": false,
    "viewers": 0,
    "thumb": null,
    "updatedAt": "2026-02-03T06:32:26.933Z"
  },
  {
    "slug": "gigidv",
    "platform": "kick",
    "live": false,
    "viewers": 0,
    "thumb": null,
    "updatedAt": "2026-02-03T06:32:26.426Z"
  },
  {
    "slug": "ikenzoo",
    "platform": "kick",
    "live": false,
    "viewers": 0,
    "thumb": null,
    "updatedAt": "2026-02-03T06:32:27.405Z"
  },
  {
    "slug": "jjuanma",
    "platform": "kick",
    "live": false,
    "viewers": 0,
    "thumb": null,
    "updatedAt": "2026-02-03T06:32:27.112Z"
  },
  {
    "slug": "jossueelsv",
    "platform": "kick",
    "live": false,
    "viewers": 0,
    "thumb": null,
    "updatedAt": "2026-02-03T06:32:26.792Z"
  },
  {
    "slug": "juniordeus",
    "platform": "kick",
    "live": false,
    "viewers": 0,
    "thumb": null,
    "updatedAt": "2026-02-03T06:32:27.556Z"
  },
  {
    "slug": "kabetotv",
    "platform": "kick",
    "live": false,
    "viewers": 0,
    "thumb": null,
    "updatedAt": "2026-02-03T06:32:24.902Z"
  },
  {
    "slug": "kattu9",
    "platform": "kick",
    "live": false,
    "viewers": 0,
    "thumb": null,
    "updatedAt": "2026-02-03T06:32:26.241Z"
  },
  {
    "slug": "kenai",
    "platform": "kick",
    "live": false,
    "viewers": 0,
    "thumb": null,
    "updatedAt": "2026-02-03T06:32:24.547Z"
  },
  {
    "slug": "kzeco",
    "platform": "kick",
    "live": false,
    "viewers": 0,
    "thumb": null,
    "updatedAt": "2026-02-03T06:32:25.527Z"
  },
  {
    "slug": "litkillah",
    "platform": "kick",
    "live": false,
    "viewers": 0,
    "thumb": null,
    "updatedAt": "2026-02-03T06:32:24.671Z"
  },
  {
    "slug": "narcovich",
    "platform": "kick",
    "live": false,
    "viewers": 0,
    "thumb": null,
    "updatedAt": "2026-02-03T06:32:25.296Z"
  },
  {
    "slug": "nohands",
    "platform": "kick",
    "live": false,
    "viewers": 0,
    "thumb": null,
    "updatedAt": "2026-02-03T06:32:25.419Z"
  },
  {
    "slug": "notbriancito",
    "platform": "kick",
    "live": false,
    "viewers": 0,
    "thumb": null,
    "updatedAt": "2026-02-03T06:32:24.936Z"
  },
  {
    "slug": "nxbraian",
    "platform": "kick",
    "live": false,
    "viewers": 0,
    "thumb": null,
    "updatedAt": "2026-02-03T06:32:26.198Z"
  },
  {
    "slug": "pioxy",
    "platform": "kick",
    "live": false,
    "viewers": 0,
    "thumb": null,
    "updatedAt": "2026-02-03T06:32:27.311Z"
  },
  {
    "slug": "qaruk",
    "platform": "kick",
    "live": false,
    "viewers": 0,
    "thumb": null,
    "updatedAt": "2026-02-03T06:32:26.925Z"
  },
  {
    "slug": "reenz",
    "platform": "kick",
    "live": false,
    "viewers": 0,
    "thumb": null,
    "updatedAt": "2026-02-03T06:32:24.778Z"
  },
  {
    "slug": "vainillitta",
    "platform": "kick",
    "live": false,
    "viewers": 0,
    "thumb": null,
    "updatedAt": "2026-02-03T06:32:26.591Z"
  },
  {
    "slug": "xxxxxxx",
    "platform": "kick",
    "live": false,
    "viewers": 0,
    "thumb": null,
    "updatedAt": "2026-02-03T06:32:24.590Z"
  }
]
