[
  {
    "slug": "9kemo",
    "platform": "kick",
    "live": false,
    "viewers": 0,
    "thumb": null,
    "updatedAt": "2025-12-21T16:33:33.459Z"
  },
  {
    "slug": "agusss04",
    "platform": "kick",
    "live": false,
    "viewers": 0,
    "thumb": null,
    "updatedAt": "2025-12-21T16:33:33.516Z"
  },
  {
    "slug": "chali",
    "platform": "kick",
    "live": false,
    "viewers": 0,
    "thumb": null,
    "updatedAt": "2025-12-21T16:33:32.511Z"
  },
  {
    "slug": "chinoxzzz",
    "platform": "kick",
    "live": false,
    "viewers": 0,
    "thumb": null,
    "updatedAt": "2025-12-21T16:33:34.236Z"
  },
  {
    "slug": "daytetona",
    "platform": "kick",
    "live": false,
    "viewers": 0,
    "thumb": null,
    "updatedAt": "2025-12-21T16:33:33.967Z"
  },
  {
    "slug": "duxontv",
    "platform": "kick",
    "live": false,
    "viewers": 0,
    "thumb": null,
    "updatedAt": "2025-12-21T16:33:34.625Z"
  },
  {
    "slug": "eldaka",
    "platform": "kick",
    "live": false,
    "viewers": 0,
    "thumb": null,
    "updatedAt": "2025-12-21T16:33:32.945Z"
  },
  {
    "slug": "feleen",
    "platform": "kick",
    "live": false,
    "viewers": 0,
    "thumb": null,
    "updatedAt": "2025-12-21T16:33:33.813Z"
  },
  {
    "slug": "ferchucabj",
    "platform": "kick",
    "live": false,
    "viewers": 0,
    "thumb": null,
    "updatedAt": "2025-12-21T16:33:33.282Z"
  },
  {
    "slug": "flakitomj",
    "platform": "kick",
    "live": false,
    "viewers": 0,
    "thumb": null,
    "updatedAt": "2025-12-21T16:33:34.445Z"
  },
  {
    "slug": "g4spl",
    "platform": "kick",
    "live": false,
    "viewers": 0,
    "thumb": null,
    "updatedAt": "2025-12-21T16:33:34.244Z"
  },
  {
    "slug": "gigidv",
    "platform": "kick",
    "live": false,
    "viewers": 0,
    "thumb": null,
    "updatedAt": "2025-12-21T16:33:33.804Z"
  },
  {
    "slug": "iemmanuel",
    "platform": "kick",
    "live": false,
    "viewers": 0,
    "thumb": null,
    "updatedAt": "2025-12-21T16:33:33.749Z"
  },
  {
    "slug": "ikenzoo",
    "platform": "kick",
    "live": false,
    "viewers": 0,
    "thumb": null,
    "updatedAt": "2025-12-21T16:33:34.348Z"
  },
  {
    "slug": "jjuanma",
    "platform": "kick",
    "live": false,
    "viewers": 0,
    "thumb": null,
    "updatedAt": "2025-12-21T16:33:34.130Z"
  },
  {
    "slug": "jossueelsv",
    "platform": "kick",
    "live": false,
    "viewers": 0,
    "thumb": null,
    "updatedAt": "2025-12-21T16:33:34.166Z"
  },
  {
    "slug": "juniordeus",
    "platform": "kick",
    "live": false,
    "viewers": 0,
    "thumb": null,
    "updatedAt": "2025-12-21T16:33:34.523Z"
  },
  {
    "slug": "kabetotv",
    "platform": "kick",
    "live": false,
    "viewers": 0,
    "thumb": null,
    "updatedAt": "2025-12-21T16:33:32.788Z"
  },
  {
    "slug": "kattu9",
    "platform": "kick",
    "live": false,
    "viewers": 0,
    "thumb": null,
    "updatedAt": "2025-12-21T16:33:33.578Z"
  },
  {
    "slug": "kenai",
    "platform": "kick",
    "live": false,
    "viewers": 0,
    "thumb": null,
    "updatedAt": "2025-12-21T16:33:32.680Z"
  },
  {
    "slug": "kzeco",
    "platform": "kick",
    "live": false,
    "viewers": 0,
    "thumb": null,
    "updatedAt": "2025-12-21T16:33:33.177Z"
  },
  {
    "slug": "litkillah",
    "platform": "kick",
    "live": false,
    "viewers": 0,
    "thumb": null,
    "updatedAt": "2025-12-21T16:33:32.432Z"
  },
  {
    "slug": "narcovich",
    "platform": "kick",
    "live": false,
    "viewers": 0,
    "thumb": null,
    "updatedAt": "2025-12-21T16:33:33.049Z"
  },
  {
    "slug": "nohands",
    "platform": "kick",
    "live": false,
    "viewers": 0,
    "thumb": null,
    "updatedAt": "2025-12-21T16:33:33.218Z"
  },
  {
    "slug": "notbriancito",
    "platform": "kick",
    "live": false,
    "viewers": 0,
    "thumb": null,
    "updatedAt": "2025-12-21T16:33:32.759Z"
  },
  {
    "slug": "nxbraian",
    "platform": "kick",
    "live": false,
    "viewers": 0,
    "thumb": null,
    "updatedAt": "2025-12-21T16:33:33.667Z"
  },
  {
    "slug": "pioxy",
    "platform": "kick",
    "live": false,
    "viewers": 0,
    "thumb": null,
    "updatedAt": "2025-12-21T16:33:34.441Z"
  },
  {
    "slug": "qaruk",
    "platform": "kick",
    "live": false,
    "viewers": 0,
    "thumb": null,
    "updatedAt": "2025-12-21T16:33:34.029Z"
  },
  {
    "slug": "reenz",
    "platform": "kick",
    "live": false,
    "viewers": 0,
    "thumb": null,
    "updatedAt": "2025-12-21T16:33:32.666Z"
  },
  {
    "slug": "vainillitta",
    "platform": "kick",
    "live": false,
    "viewers": 0,
    "thumb": null,
    "updatedAt": "2025-12-21T16:33:33.879Z"
  },
  {
    "slug": "xxxxxxx",
    "platform": "kick",
    "live": false,
    "viewers": 0,
    "thumb": null,
    "updatedAt": "2025-12-21T16:33:32.422Z"
  }
]
