[
  {
    "slug": "chali",
    "platform": "kick",
    "live": true,
    "viewers": 0,
    "thumb": "https://stream.kick.com/thumbnails/livestream/84487500/thumb0/video_thumbnail/thumb0.jpg",
    "updatedAt": "2025-11-21T08:37:50.708Z"
  },
  {
    "slug": "9kemo",
    "platform": "kick",
    "live": false,
    "viewers": 0,
    "thumb": null,
    "updatedAt": "2025-11-21T08:37:51.775Z"
  },
  {
    "slug": "agusss04",
    "platform": "kick",
    "live": false,
    "viewers": 0,
    "thumb": null,
    "updatedAt": "2025-11-21T08:37:51.617Z"
  },
  {
    "slug": "chinoxzzz",
    "platform": "kick",
    "live": false,
    "viewers": 0,
    "thumb": null,
    "updatedAt": "2025-11-21T08:37:53.069Z"
  },
  {
    "slug": "daytetona",
    "platform": "kick",
    "live": false,
    "viewers": 0,
    "thumb": null,
    "updatedAt": "2025-11-21T08:37:52.616Z"
  },
  {
    "slug": "duxontv",
    "platform": "kick",
    "live": false,
    "viewers": 0,
    "thumb": null,
    "updatedAt": "2025-11-21T08:37:53.379Z"
  },
  {
    "slug": "eldaka",
    "platform": "kick",
    "live": false,
    "viewers": 0,
    "thumb": null,
    "updatedAt": "2025-11-21T08:37:51.140Z"
  },
  {
    "slug": "feleen",
    "platform": "kick",
    "live": false,
    "viewers": 0,
    "thumb": null,
    "updatedAt": "2025-11-21T08:37:52.145Z"
  },
  {
    "slug": "ferchucabj",
    "platform": "kick",
    "live": false,
    "viewers": 0,
    "thumb": null,
    "updatedAt": "2025-11-21T08:37:51.466Z"
  },
  {
    "slug": "flakitomj",
    "platform": "kick",
    "live": false,
    "viewers": 0,
    "thumb": null,
    "updatedAt": "2025-11-21T08:37:53.019Z"
  },
  {
    "slug": "g4spl",
    "platform": "kick",
    "live": false,
    "viewers": 0,
    "thumb": null,
    "updatedAt": "2025-11-21T08:37:53.050Z"
  },
  {
    "slug": "gigidv",
    "platform": "kick",
    "live": false,
    "viewers": 0,
    "thumb": null,
    "updatedAt": "2025-11-21T08:37:52.347Z"
  },
  {
    "slug": "iemmanuel",
    "platform": "kick",
    "live": false,
    "viewers": 0,
    "thumb": null,
    "updatedAt": "2025-11-21T08:37:52.063Z"
  },
  {
    "slug": "ikenzoo",
    "platform": "kick",
    "live": false,
    "viewers": 0,
    "thumb": null,
    "updatedAt": "2025-11-21T08:37:53.079Z"
  },
  {
    "slug": "jjuanma",
    "platform": "kick",
    "live": false,
    "viewers": 0,
    "thumb": null,
    "updatedAt": "2025-11-21T08:37:52.633Z"
  },
  {
    "slug": "jossueelsv",
    "platform": "kick",
    "live": false,
    "viewers": 0,
    "thumb": null,
    "updatedAt": "2025-11-21T08:37:52.526Z"
  },
  {
    "slug": "juniordeus",
    "platform": "kick",
    "live": false,
    "viewers": 0,
    "thumb": null,
    "updatedAt": "2025-11-21T08:37:53.761Z"
  },
  {
    "slug": "kabetotv",
    "platform": "kick",
    "live": false,
    "viewers": 0,
    "thumb": null,
    "updatedAt": "2025-11-21T08:37:50.844Z"
  },
  {
    "slug": "kattu9",
    "platform": "kick",
    "live": false,
    "viewers": 0,
    "thumb": null,
    "updatedAt": "2025-11-21T08:37:51.831Z"
  },
  {
    "slug": "kenai",
    "platform": "kick",
    "live": false,
    "viewers": 0,
    "thumb": null,
    "updatedAt": "2025-11-21T08:37:50.854Z"
  },
  {
    "slug": "kzeco",
    "platform": "kick",
    "live": false,
    "viewers": 0,
    "thumb": null,
    "updatedAt": "2025-11-21T08:37:51.529Z"
  },
  {
    "slug": "litkillah",
    "platform": "kick",
    "live": false,
    "viewers": 0,
    "thumb": null,
    "updatedAt": "2025-11-21T08:37:50.401Z"
  },
  {
    "slug": "narcovich",
    "platform": "kick",
    "live": false,
    "viewers": 0,
    "thumb": null,
    "updatedAt": "2025-11-21T08:37:51.533Z"
  },
  {
    "slug": "nohands",
    "platform": "kick",
    "live": false,
    "viewers": 0,
    "thumb": null,
    "updatedAt": "2025-11-21T08:37:51.120Z"
  },
  {
    "slug": "notbriancito",
    "platform": "kick",
    "live": false,
    "viewers": 0,
    "thumb": null,
    "updatedAt": "2025-11-21T08:37:51.071Z"
  },
  {
    "slug": "nxbraian",
    "platform": "kick",
    "live": false,
    "viewers": 0,
    "thumb": null,
    "updatedAt": "2025-11-21T08:37:51.944Z"
  },
  {
    "slug": "pioxy",
    "platform": "kick",
    "live": false,
    "viewers": 0,
    "thumb": null,
    "updatedAt": "2025-11-21T08:37:53.108Z"
  },
  {
    "slug": "qaruk",
    "platform": "kick",
    "live": false,
    "viewers": 0,
    "thumb": null,
    "updatedAt": "2025-11-21T08:37:52.581Z"
  },
  {
    "slug": "reenz",
    "platform": "kick",
    "live": false,
    "viewers": 0,
    "thumb": null,
    "updatedAt": "2025-11-21T08:37:50.884Z"
  },
  {
    "slug": "vainillitta",
    "platform": "kick",
    "live": false,
    "viewers": 0,
    "thumb": null,
    "updatedAt": "2025-11-21T08:37:52.209Z"
  },
  {
    "slug": "xxxxxxx",
    "platform": "kick",
    "live": false,
    "viewers": 0,
    "thumb": null,
    "updatedAt": "2025-11-21T08:37:50.612Z"
  }
]
