[
  {
    "slug": "iemmanuel",
    "platform": "kick",
    "live": true,
    "viewers": 0,
    "thumb": null,
    "updatedAt": "2025-12-17T17:43:06.530Z"
  },
  {
    "slug": "jjuanma",
    "platform": "kick",
    "live": true,
    "viewers": 0,
    "thumb": null,
    "updatedAt": "2025-12-17T17:43:06.966Z"
  },
  {
    "slug": "9kemo",
    "platform": "kick",
    "live": false,
    "viewers": 0,
    "thumb": null,
    "updatedAt": "2025-12-17T17:43:06.143Z"
  },
  {
    "slug": "agusss04",
    "platform": "kick",
    "live": false,
    "viewers": 0,
    "thumb": null,
    "updatedAt": "2025-12-17T17:43:05.972Z"
  },
  {
    "slug": "chali",
    "platform": "kick",
    "live": false,
    "viewers": 0,
    "thumb": null,
    "updatedAt": "2025-12-17T17:43:05.297Z"
  },
  {
    "slug": "chinoxzzz",
    "platform": "kick",
    "live": false,
    "viewers": 0,
    "thumb": null,
    "updatedAt": "2025-12-17T17:43:07.048Z"
  },
  {
    "slug": "daytetona",
    "platform": "kick",
    "live": false,
    "viewers": 0,
    "thumb": null,
    "updatedAt": "2025-12-17T17:43:06.772Z"
  },
  {
    "slug": "duxontv",
    "platform": "kick",
    "live": false,
    "viewers": 0,
    "thumb": null,
    "updatedAt": "2025-12-17T17:43:07.465Z"
  },
  {
    "slug": "eldaka",
    "platform": "kick",
    "live": false,
    "viewers": 0,
    "thumb": null,
    "updatedAt": "2025-12-17T17:43:05.593Z"
  },
  {
    "slug": "feleen",
    "platform": "kick",
    "live": false,
    "viewers": 0,
    "thumb": null,
    "updatedAt": "2025-12-17T17:43:06.386Z"
  },
  {
    "slug": "ferchucabj",
    "platform": "kick",
    "live": false,
    "viewers": 0,
    "thumb": null,
    "updatedAt": "2025-12-17T17:43:06.056Z"
  },
  {
    "slug": "flakitomj",
    "platform": "kick",
    "live": false,
    "viewers": 0,
    "thumb": null,
    "updatedAt": "2025-12-17T17:43:07.190Z"
  },
  {
    "slug": "g4spl",
    "platform": "kick",
    "live": false,
    "viewers": 0,
    "thumb": null,
    "updatedAt": "2025-12-17T17:43:06.978Z"
  },
  {
    "slug": "gigidv",
    "platform": "kick",
    "live": false,
    "viewers": 0,
    "thumb": null,
    "updatedAt": "2025-12-17T17:43:06.448Z"
  },
  {
    "slug": "ikenzoo",
    "platform": "kick",
    "live": false,
    "viewers": 0,
    "thumb": null,
    "updatedAt": "2025-12-17T17:43:07.151Z"
  },
  {
    "slug": "jossueelsv",
    "platform": "kick",
    "live": false,
    "viewers": 0,
    "thumb": null,
    "updatedAt": "2025-12-17T17:43:06.883Z"
  },
  {
    "slug": "juniordeus",
    "platform": "kick",
    "live": false,
    "viewers": 0,
    "thumb": null,
    "updatedAt": "2025-12-17T17:43:07.325Z"
  },
  {
    "slug": "kabetotv",
    "platform": "kick",
    "live": false,
    "viewers": 0,
    "thumb": null,
    "updatedAt": "2025-12-17T17:43:05.573Z"
  },
  {
    "slug": "kattu9",
    "platform": "kick",
    "live": false,
    "viewers": 0,
    "thumb": null,
    "updatedAt": "2025-12-17T17:43:06.363Z"
  },
  {
    "slug": "kenai",
    "platform": "kick",
    "live": false,
    "viewers": 0,
    "thumb": null,
    "updatedAt": "2025-12-17T17:43:05.448Z"
  },
  {
    "slug": "kzeco",
    "platform": "kick",
    "live": false,
    "viewers": 0,
    "thumb": null,
    "updatedAt": "2025-12-17T17:43:06.045Z"
  },
  {
    "slug": "litkillah",
    "platform": "kick",
    "live": false,
    "viewers": 0,
    "thumb": null,
    "updatedAt": "2025-12-17T17:43:05.236Z"
  },
  {
    "slug": "narcovich",
    "platform": "kick",
    "live": false,
    "viewers": 0,
    "thumb": null,
    "updatedAt": "2025-12-17T17:43:05.801Z"
  },
  {
    "slug": "nohands",
    "platform": "kick",
    "live": false,
    "viewers": 0,
    "thumb": null,
    "updatedAt": "2025-12-17T17:43:05.959Z"
  },
  {
    "slug": "notbriancito",
    "platform": "kick",
    "live": false,
    "viewers": 0,
    "thumb": null,
    "updatedAt": "2025-12-17T17:43:05.616Z"
  },
  {
    "slug": "nxbraian",
    "platform": "kick",
    "live": false,
    "viewers": 0,
    "thumb": null,
    "updatedAt": "2025-12-17T17:43:06.394Z"
  },
  {
    "slug": "pioxy",
    "platform": "kick",
    "live": false,
    "viewers": 0,
    "thumb": null,
    "updatedAt": "2025-12-17T17:43:07.361Z"
  },
  {
    "slug": "qaruk",
    "platform": "kick",
    "live": false,
    "viewers": 0,
    "thumb": null,
    "updatedAt": "2025-12-17T17:43:06.846Z"
  },
  {
    "slug": "reenz",
    "platform": "kick",
    "live": false,
    "viewers": 0,
    "thumb": null,
    "updatedAt": "2025-12-17T17:43:05.406Z"
  },
  {
    "slug": "vainillitta",
    "platform": "kick",
    "live": false,
    "viewers": 0,
    "thumb": null,
    "updatedAt": "2025-12-17T17:43:06.580Z"
  },
  {
    "slug": "xxxxxxx",
    "platform": "kick",
    "live": false,
    "viewers": 0,
    "thumb": null,
    "updatedAt": "2025-12-17T17:43:05.186Z"
  }
]
