[
  {
    "slug": "g4spl",
    "platform": "kick",
    "live": true,
    "viewers": 0,
    "thumb": "https://stream.kick.com/thumbnails/livestream/91363434/thumb0/video_thumbnail/thumb0.jpg",
    "updatedAt": "2026-01-10T16:34:57.957Z"
  },
  {
    "slug": "9kemo",
    "platform": "kick",
    "live": false,
    "viewers": 0,
    "thumb": null,
    "updatedAt": "2026-01-10T16:34:56.927Z"
  },
  {
    "slug": "agusss04",
    "platform": "kick",
    "live": false,
    "viewers": 0,
    "thumb": null,
    "updatedAt": "2026-01-10T16:34:56.859Z"
  },
  {
    "slug": "chali",
    "platform": "kick",
    "live": false,
    "viewers": 0,
    "thumb": null,
    "updatedAt": "2026-01-10T16:34:55.757Z"
  },
  {
    "slug": "chinoxzzz",
    "platform": "kick",
    "live": false,
    "viewers": 0,
    "thumb": null,
    "updatedAt": "2026-01-10T16:34:58.150Z"
  },
  {
    "slug": "daytetona",
    "platform": "kick",
    "live": false,
    "viewers": 0,
    "thumb": null,
    "updatedAt": "2026-01-10T16:34:57.631Z"
  },
  {
    "slug": "duxontv",
    "platform": "kick",
    "live": false,
    "viewers": 0,
    "thumb": null,
    "updatedAt": "2026-01-10T16:34:58.780Z"
  },
  {
    "slug": "eldaka",
    "platform": "kick",
    "live": false,
    "viewers": 0,
    "thumb": null,
    "updatedAt": "2026-01-10T16:34:56.237Z"
  },
  {
    "slug": "feleen",
    "platform": "kick",
    "live": false,
    "viewers": 0,
    "thumb": null,
    "updatedAt": "2026-01-10T16:34:57.089Z"
  },
  {
    "slug": "ferchucabj",
    "platform": "kick",
    "live": false,
    "viewers": 0,
    "thumb": null,
    "updatedAt": "2026-01-10T16:34:56.400Z"
  },
  {
    "slug": "flakitomj",
    "platform": "kick",
    "live": false,
    "viewers": 0,
    "thumb": null,
    "updatedAt": "2026-01-10T16:34:58.271Z"
  },
  {
    "slug": "gigidv",
    "platform": "kick",
    "live": false,
    "viewers": 0,
    "thumb": null,
    "updatedAt": "2026-01-10T16:34:57.154Z"
  },
  {
    "slug": "iemmanuel",
    "platform": "kick",
    "live": false,
    "viewers": 0,
    "thumb": null,
    "updatedAt": "2026-01-10T16:34:56.782Z"
  },
  {
    "slug": "ikenzoo",
    "platform": "kick",
    "live": false,
    "viewers": 0,
    "thumb": null,
    "updatedAt": "2026-01-10T16:34:58.257Z"
  },
  {
    "slug": "jjuanma",
    "platform": "kick",
    "live": false,
    "viewers": 0,
    "thumb": null,
    "updatedAt": "2026-01-10T16:34:57.810Z"
  },
  {
    "slug": "jossueelsv",
    "platform": "kick",
    "live": false,
    "viewers": 0,
    "thumb": null,
    "updatedAt": "2026-01-10T16:34:57.775Z"
  },
  {
    "slug": "juniordeus",
    "platform": "kick",
    "live": false,
    "viewers": 0,
    "thumb": null,
    "updatedAt": "2026-01-10T16:34:58.357Z"
  },
  {
    "slug": "kabetotv",
    "platform": "kick",
    "live": false,
    "viewers": 0,
    "thumb": null,
    "updatedAt": "2026-01-10T16:34:55.967Z"
  },
  {
    "slug": "kattu9",
    "platform": "kick",
    "live": false,
    "viewers": 0,
    "thumb": null,
    "updatedAt": "2026-01-10T16:34:57.048Z"
  },
  {
    "slug": "kenai",
    "platform": "kick",
    "live": false,
    "viewers": 0,
    "thumb": null,
    "updatedAt": "2026-01-10T16:34:55.586Z"
  },
  {
    "slug": "kzeco",
    "platform": "kick",
    "live": false,
    "viewers": 0,
    "thumb": null,
    "updatedAt": "2026-01-10T16:34:56.387Z"
  },
  {
    "slug": "litkillah",
    "platform": "kick",
    "live": false,
    "viewers": 0,
    "thumb": null,
    "updatedAt": "2026-01-10T16:34:55.716Z"
  },
  {
    "slug": "narcovich",
    "platform": "kick",
    "live": false,
    "viewers": 0,
    "thumb": null,
    "updatedAt": "2026-01-10T16:34:56.345Z"
  },
  {
    "slug": "nohands",
    "platform": "kick",
    "live": false,
    "viewers": 0,
    "thumb": null,
    "updatedAt": "2026-01-10T16:34:56.334Z"
  },
  {
    "slug": "notbriancito",
    "platform": "kick",
    "live": false,
    "viewers": 0,
    "thumb": null,
    "updatedAt": "2026-01-10T16:34:56.010Z"
  },
  {
    "slug": "nxbraian",
    "platform": "kick",
    "live": false,
    "viewers": 0,
    "thumb": null,
    "updatedAt": "2026-01-10T16:34:57.100Z"
  },
  {
    "slug": "pioxy",
    "platform": "kick",
    "live": false,
    "viewers": 0,
    "thumb": null,
    "updatedAt": "2026-01-10T16:34:58.133Z"
  },
  {
    "slug": "qaruk",
    "platform": "kick",
    "live": false,
    "viewers": 0,
    "thumb": null,
    "updatedAt": "2026-01-10T16:34:57.736Z"
  },
  {
    "slug": "reenz",
    "platform": "kick",
    "live": false,
    "viewers": 0,
    "thumb": null,
    "updatedAt": "2026-01-10T16:34:55.829Z"
  },
  {
    "slug": "vainillitta",
    "platform": "kick",
    "live": false,
    "viewers": 0,
    "thumb": null,
    "updatedAt": "2026-01-10T16:34:57.451Z"
  },
  {
    "slug": "xxxxxxx",
    "platform": "kick",
    "live": false,
    "viewers": 0,
    "thumb": null,
    "updatedAt": "2026-01-10T16:34:55.575Z"
  }
]
